lazylinks/__init__.py
lazylinks/dotdict.py
lazylinks/lazylinks.mako
lazylinks/lazylinks.py
lazylinks/wrap.mako
lazylinks-0.1.2.dist-info/LICENSE
lazylinks-0.1.2.dist-info/METADATA
lazylinks-0.1.2.dist-info/WHEEL
lazylinks-0.1.2.dist-info/entry_points.txt
lazylinks-0.1.2.dist-info/top_level.txt
lazylinks-0.1.2.dist-info/RECORD
