Metadata-Version: 2.1
Name: lazylinks
Version: 0.1.2
Summary: Linktree-style links for lazy people
Author-email: Samuel Colburn <samuel.colburn@gmail.com>
License: MIT License
Classifier: Programming Language :: Python :: 3
Classifier: License :: OSI Approved :: MIT License
Requires-Python: >=3.7
License-File: LICENSE
Requires-Dist: Mako (==1.2.4)
Requires-Dist: PyYAML (==6.0)
